MANIFEST.in
README.md
setup.cfg
setup.py
bin/nbpipeline
examples/__init__.py
examples/pipeline.py
nbpipeline/__init__.py
nbpipeline/graph.py
nbpipeline/io.py
nbpipeline/nbpipeline.py
nbpipeline/rules.py
nbpipeline/utils.py
nbpipeline.egg-info/PKG-INFO
nbpipeline.egg-info/SOURCES.txt
nbpipeline.egg-info/dependency_links.txt
nbpipeline.egg-info/requires.txt
nbpipeline.egg-info/top_level.txt
nbpipeline/version_control/__init__.py
nbpipeline/version_control/git.py
nbpipeline/visualization/__init__.py
nbpipeline/visualization/interactive_graph.py
nbpipeline/visualization/static_graph.py
nbpipeline/visualization/__pycache__/__init__.cpython-37.pyc
nbpipeline/visualization/__pycache__/__init__.cpython-38.pyc
nbpipeline/visualization/__pycache__/interactive_graph.cpython-37.pyc
nbpipeline/visualization/__pycache__/interactive_graph.cpython-38.pyc
nbpipeline/visualization/__pycache__/static_graph.cpython-37.pyc
nbpipeline/visualization/__pycache__/static_graph.cpython-38.pyc
nbpipeline/visualization/templates/graph.html
nbpipeline/visualization/templates/static/graph.css
nbpipeline/visualization/templates/static/style.css