Metadata-Version: 1.1
Name: nbpipeline
Version: 0.2.7
Summary: Snakemake-like pipeline manager for reproducible Jupyter Notebooks
Home-page: https://github.com/krassowski/nbpipeline
Author: Michal Krassowski
Author-email: krassowski.michal+pypi@gmail.com
License: MIT
Keywords: snakemake,pipeline,reproducible,jupyter,notebooks
Platform: UNKNOWN
Classifier: Development Status :: 4 - Beta
Classifier: License :: OSI Approved :: MIT License
Classifier: Operating System :: Microsoft :: Windows
Classifier: Operating System :: POSIX :: Linux
Classifier: Topic :: Utilities
Classifier: Topic :: Software Development :: Libraries :: Python Modules
Classifier: Intended Audience :: Developers
Classifier: Intended Audience :: Science/Research
Classifier: Programming Language :: Python :: 3.6
Classifier: Programming Language :: Python :: 3.7
Classifier: Programming Language :: Python :: 3.8
